{
  "schemaVersion": 1,
  "updatedAt": "2026-06-24T00:00:00.000Z",
  "recipes": [
    {
      "id": "award-gala",
      "title": "Award-Show / Gala",
      "category": "Veranstaltungsformate",
      "difficulty": "anspruchsvoll",
      "setupTimeMin": 720,
      "teamSize": "5-8",
      "tags": [
        "award",
        "gala",
        "show",
        "einspieler",
        "buehne",
        "streaming"
      ],
      "relatedTools": [
        "jm-rundown",
        "jm-switcher",
        "jm-titler",
        "jm-player",
        "jm-timer",
        "jm-recorder"
      ],
      "prerequisites": [
        "Bühne mit kameragerechter Ausleuchtung",
        "Mehrere Kameras (Totale + Nah + Bühne)",
        "Einspieler/Trailer und Musik-Cues bereit",
        "Regieplan/Rundown und Moderation"
      ],
      "equipmentOwner": "gemischt",
      "crewRoles": [
        "Regie",
        "Bildmischung",
        "Audio",
        "Grafik / Titler",
        "Zuspielung / Einspieler",
        "Licht"
      ],
      "lastReviewed": "2026-06-24",
      "owner": "tech@jakobsmedien.com",
      "summary": "Preisverleihung/Gala mit Show-Charakter — Einspieler, Gewinner-Reveals, Laudationes, Live-Bauchbinden und saubere Ablaufregie.",
      "blocks": {
        "ingredients": [
          {
            "title": "Bühne & Licht",
            "items": [
              "Kameragerechte Ausleuchtung",
              "Bühnenvorschau"
            ]
          },
          {
            "title": "Video",
            "items": [
              "Multicam (Totale + Nah + Bühne)",
              "Bildmischer + Aufzeichnung (JM Recorder/Switcher)"
            ]
          },
          {
            "title": "Grafik",
            "items": [
              "Lower Thirds / VS-Bauchbinden (JM Titler)",
              "Nominierten- und Gewinner-Grafiken"
            ]
          },
          {
            "title": "Zuspielung & Ablauf",
            "items": [
              "Einspieler/Trailer (JM Player), Musik-Cues",
              "Rundown (JM Rundown) für Segmente und GO"
            ]
          },
          {
            "title": "Rollen",
            "items": [
              "Regie, Bildmischung, Audio, Grafik, Zuspielung, Licht"
            ]
          }
        ],
        "steps": {
          "vor": [
            "Rundown je Programmpunkt anlegen (Einspieler, Titler, Szene)",
            "Einspieler in JM Player laden, Reihenfolge prüfen",
            "Bauchbinden/Reveal-Grafiken vorbereiten",
            "Generalprobe mit dem kompletten Ablauf"
          ],
          "waehrend": [
            "Regie folgt dem Rundown (GO pro Segment)",
            "Gewinner-Reveals sauber timen (Musik + Titler + Schnitt)",
            "Bauchbinden takten, Einspieler/Musik cuen",
            "Aufzeichnung mitlaufen lassen"
          ],
          "nach": [
            "Aufzeichnung sichern",
            "Highlight-Schnitt vorbereiten, Material übergeben"
          ]
        },
        "troubleshooting": [
          {
            "risk": "Einspieler startet nicht",
            "remedy": "Backup-Kopie + zweiter Player bereit"
          },
          {
            "risk": "Falsche/keine Bauchbinde",
            "remedy": "Im Rundown gepflegt? Titler im LAN?"
          },
          {
            "risk": "Ablauf verrutscht",
            "remedy": "Puffer im Rundown, Segmente kürzbar planen"
          }
        ],
        "checklists": [
          {
            "title": "Vorbereitung",
            "items": [
              "Rundown je Segment angelegt",
              "Einspieler geladen und sortiert",
              "Bauchbinden/Reveal-Grafiken bereit",
              "Generalprobe gelaufen"
            ]
          },
          {
            "title": "Show",
            "items": [
              "GO je Segment getestet",
              "Aufzeichnung armiert",
              "Musik/Cues bereit"
            ]
          }
        ],
        "tips": [
          "Reveal-Momente proben — das Zusammenspiel von Musik, Bauchbinde und Schnitt macht den Effekt.",
          "Reihenfolge der Bauchbinden vorab in den Rundown legen, nicht live suchen."
        ]
      }
    },
    {
      "id": "hybrid-konferenz",
      "title": "Hybrid-Konferenz",
      "category": "Veranstaltungsformate",
      "difficulty": "anspruchsvoll",
      "setupTimeMin": 480,
      "teamSize": "4-6",
      "tags": [
        "hybrid",
        "streaming",
        "konferenz",
        "regie"
      ],
      "relatedTools": [
        "jm-rundown",
        "jm-switcher",
        "jm-caption",
        "jm-timer",
        "jm-prompter"
      ],
      "prerequisites": [
        "Stabile Upload-Leitung (mind. 10 Mbit/s)",
        "Backup-Internet (Mobile-Hotspot)",
        "Separate Mischpulte für Saal und Stream"
      ],
      "equipmentOwner": "jm",
      "crewRoles": [
        "Eventleitung",
        "Technische Leitung",
        "Regie",
        "Moderator / Host",
        "Streaming-Operator",
        "Chat- / Remote-Betreuung"
      ],
      "lastReviewed": "2026-06-24",
      "owner": "tech@jakobsmedien.com",
      "summary": "Physische und digitale Teilnehmende in einem gemeinsamen Event-Erlebnis — gleichwertig, professionell, technisch redundant.",
      "blocks": {
        "ingredients": [
          {
            "title": "Audio",
            "items": [
              "Saubere Mikrofonierung (Headsets bevorzugt)",
              "Separate Mischpulte für Saal und Stream",
              "Echo- und Feedback-Vermeidung"
            ]
          },
          {
            "title": "Video",
            "items": [
              "Mindestens 2 Kameras (Totale + Close-Up)",
              "Saubere Ausleuchtung",
              "Klare Bildkomposition"
            ]
          },
          {
            "title": "Streaming",
            "items": [
              "OBS, vMix oder Hardware-Encoder",
              "Stabile Upload-Leitung (mind. 10 Mbit/s)",
              "Backup-Stream"
            ]
          },
          {
            "title": "Backup-Systeme",
            "items": [
              "Ersatzmikrofone",
              "Zweiter Laptop für Präsentationen",
              "Redundante Internetverbindung"
            ]
          },
          {
            "title": "Rollen / Personal",
            "items": [
              "Eventleitung (Gesamtverantwortung, Freigaben)",
              "Technische Leitung (koordiniert alle Gewerke)",
              "Regie (Ablaufsteuerung, Kommunikation Bühne/Technik/Remote)",
              "Moderator / Host (führt durchs Programm, bindet Remote ein)",
              "Streaming-Operator (Szenenwechsel, Einspieler, Overlays)",
              "Chat- / Remote-Betreuung (filtert und leitet Fragen weiter)"
            ]
          }
        ],
        "steps": {
          "vor": [
            "Technik-Check aller Gewerke",
            "Soundcheck (Saal und Stream getrennt)",
            "Kamerapositionen festlegen",
            "Präsentationen testen",
            "Teilnehmerzugänge testen",
            "Moderator briefen, Regieplan verteilen, Chat-Team einweisen"
          ],
          "waehrend": [
            "Regie steuert Szenenwechsel",
            "Moderator interagiert aktiv mit Remote-Teilnehmenden",
            "Chat-Team filtert Fragen und leitet sie an die Bühne weiter"
          ],
          "nach": [
            "Aufzeichnung sichern",
            "Feedback einholen",
            "Material an Kunden senden"
          ]
        },
        "troubleshooting": [
          {
            "risk": "Internet bricht ab",
            "remedy": "Mobile-Hotspot als Backup, Backup-Stream vorbereitet halten"
          },
          {
            "risk": "Mikrofon fällt aus",
            "remedy": "Ersatzmikrofon griffbereit bereitstellen"
          },
          {
            "risk": "Präsentation startet nicht",
            "remedy": "Zweiter Laptop mit gespiegelten Folien"
          },
          {
            "risk": "Kameraausfall",
            "remedy": "Ersatzkamera oder kurzfristig auf Totale umschalten"
          },
          {
            "risk": "Verzögerungen im Ablauf",
            "remedy": "Regieplan mit Puffern, Segmente kürzbar planen"
          }
        ],
        "checklists": [
          {
            "title": "Technik-Checkliste",
            "items": [
              "Mikrofone geladen",
              "Kameras eingerichtet",
              "Streaming getestet",
              "Präsentationen geprüft",
              "Backup-Systeme bereit"
            ]
          },
          {
            "title": "Ablauf-Checkliste",
            "items": [
              "Moderator gebrieft",
              "Regieplan verteilt",
              "Teilnehmerzugänge getestet",
              "Chat-Team eingewiesen"
            ]
          }
        ],
        "tips": [
          "Gleichwertiges Erlebnis für beide Gruppen aktiv mitdenken — Remote nicht als Publikum zweiter Klasse behandeln.",
          "Regieplan mit Puffern bauen, um Verzögerungen abzufangen."
        ]
      }
    },
    {
      "id": "townhall",
      "title": "Townhall / Mitarbeiterversammlung (hybrid)",
      "category": "Veranstaltungsformate",
      "difficulty": "mittel",
      "setupTimeMin": 300,
      "teamSize": "3-4",
      "tags": [
        "townhall",
        "hybrid",
        "intern",
        "qa",
        "streaming"
      ],
      "relatedTools": [
        "jm-switcher",
        "jm-qa",
        "jm-caption",
        "jm-timer",
        "jm-presenter"
      ],
      "prerequisites": [
        "Stabile Upload-Leitung + Backup",
        "Interne Stream-Plattform/Zugang (DSGVO-konform)",
        "Saalmikrofonierung für Fragen",
        "Q&A-Kanal (QR fürs Handy)"
      ],
      "equipmentOwner": "jm",
      "crewRoles": [
        "Regie",
        "Streaming-Operator",
        "Q&A-/Moderations-Betreuung",
        "Audio"
      ],
      "lastReviewed": "2026-06-24",
      "owner": "tech@jakobsmedien.com",
      "summary": "Interne Mitarbeiterversammlung, hybrid: Führungsteam auf der Bühne, Belegschaft vor Ort und im Stream, mit moderierter Fragerunde.",
      "blocks": {
        "ingredients": [
          {
            "title": "Audio",
            "items": [
              "Headsets/Handmikros fürs Panel",
              "Saalmikrofon(e) für Publikumsfragen",
              "Getrennter Saal- und Stream-Mix"
            ]
          },
          {
            "title": "Video",
            "items": [
              "1–2 Kameras (Totale/Bühne)",
              "Folien als sauberer Bildanteil (JM Presenter)"
            ]
          },
          {
            "title": "Streaming & Interaktion",
            "items": [
              "Interne Plattform (DSGVO), stabiler Upload, Backup",
              "Moderierte Fragen via JM Q&A (QR fürs Handy)",
              "Optional Untertitel (JM Caption) für Barrierefreiheit"
            ]
          },
          {
            "title": "Rollen",
            "items": [
              "Regie, Streaming-Operator, Q&A-Moderation, Audio"
            ]
          }
        ],
        "steps": {
          "vor": [
            "Plattform und Zugänge testen",
            "Folien (JM Presenter) prüfen",
            "Q&A + QR vorbereiten, Moderationsschritt einstellen",
            "Soundcheck Panel + Saalmikro",
            "Probe der Fragerunde"
          ],
          "waehrend": [
            "Regie schaltet Bühne und Folien",
            "Q&A-Moderation filtert Fragen, holt per Klick ans Wort (Timer + Bauchbinde)",
            "Stream-Gesundheit beobachten"
          ],
          "nach": [
            "Aufzeichnung intern bereitstellen",
            "Offene Fragen / Backlog dokumentieren"
          ]
        },
        "troubleshooting": [
          {
            "risk": "Zu wenige Fragen",
            "remedy": "Vorab-Sammelphase + vorbereitete Moderationsfragen"
          },
          {
            "risk": "Feedback am Saalmikro",
            "remedy": "Pegel/Position prüfen, Richtung PA meiden"
          },
          {
            "risk": "Interner Stream nicht erreichbar",
            "remedy": "Zugang/VPN prüfen, Backup-Pfad bereithalten"
          }
        ],
        "checklists": [
          {
            "title": "Vorbereitung",
            "items": [
              "Plattform und Zugänge getestet",
              "Folien geprüft",
              "Q&A/QR bereit, Moderation gesetzt",
              "Soundcheck Panel + Saalmikro"
            ]
          },
          {
            "title": "Vor Live",
            "items": [
              "Fragerunde geprobt",
              "Stream getestet",
              "Backup bereit"
            ]
          }
        ],
        "tips": [
          "Fragen vorab sammeln lassen — hält die Runde fokussiert und füllt Leerlauf.",
          "Untertitel erhöhen Reichweite und Barrierefreiheit, besonders bei großen Belegschaften."
        ]
      }
    },
    {
      "id": "audio-grundsetup",
      "title": "Audio-Grundsetup für Events",
      "category": "Technik-Setups",
      "difficulty": "mittel",
      "setupTimeMin": 90,
      "teamSize": "1",
      "tags": [
        "audio",
        "mischpult",
        "funkstrecken",
        "monitoring",
        "feedback"
      ],
      "relatedTools": [
        "jm-recorder",
        "jm-switcher"
      ],
      "prerequisites": [
        "Mischpult mit ausreichend Kanälen (ggf. Stagebox)",
        "Funkstrecken/Mikrofone inkl. Reserve-Set",
        "Monitoring (Kopfhörer/Abhöre, ggf. Bühnenmonitor)",
        "Abgesicherte Stromversorgung"
      ],
      "equipmentOwner": "jm",
      "crewRoles": [
        "Media Operator Audio"
      ],
      "lastReviewed": "2026-06-24",
      "owner": "tech@jakobsmedien.com",
      "summary": "Sauberes Audio-Grundsetup für Events — Mikrofonierung, getrennter Saal-/Stream-Mix, Monitoring und Feedback-Vermeidung. Modularer Baustein für Konferenz, Townhall, Gala.",
      "blocks": {
        "ingredients": [
          {
            "title": "Pult & Wandlung",
            "items": [
              "Mischpult mit ausreichend Kanälen, ggf. Stagebox",
              "Saubere Stromversorgung"
            ]
          },
          {
            "title": "Mikrofone",
            "items": [
              "Funkstrecken (Headset/Handheld) + Reserve-Set",
              "Frequenzplanung/Koordination"
            ]
          },
          {
            "title": "Mixe & Monitoring",
            "items": [
              "Getrennter Saal-PA-Mix und Stream-/Aufnahme-Mix",
              "Operator-Abhöre, optional Bühnenmonitoring"
            ]
          }
        ],
        "steps": {
          "vor": [
            "Kanäle anlegen und beschriften",
            "Funkstrecken einmessen (Frequenzen koordinieren)",
            "Gain/Pegel einstellen",
            "Saal- und Stream-Mix sauber trennen",
            "Feedback-Punkte vorab ausreizen"
          ],
          "waehrend": [
            "Pegel fahren, diszipliniert muten",
            "Funkbatterien und Empfang im Blick",
            "Stream-Pegel stabil halten"
          ],
          "nach": [
            "Aufnahme sichern",
            "Funkstrecken laden"
          ]
        },
        "troubleshooting": [
          {
            "risk": "Feedback / Rückkopplung",
            "remedy": "Pegel/Position/EQ, Mikro nicht Richtung PA"
          },
          {
            "risk": "Funkaussetzer",
            "remedy": "Frequenz/Antenne prüfen, Batterie tauschen"
          },
          {
            "risk": "Brummen",
            "remedy": "Masseschleife prüfen, DI-Box einsetzen"
          }
        ],
        "checklists": [
          {
            "title": "Aufbau",
            "items": [
              "Kanäle beschriftet",
              "Funkstrecken eingemessen",
              "Saal- und Stream-Mix getrennt",
              "Monitoring steht"
            ]
          },
          {
            "title": "Vor Live",
            "items": [
              "Soundcheck aller Mikros",
              "Batterien frisch",
              "Stream-Pegel ok"
            ]
          }
        ],
        "tips": [
          "Saal- und Stream-Mix immer trennen — der Saal braucht etwas anderes als der Stream.",
          "Reserve-Funkstrecke und Ersatzbatterien gehören immer ins Setup."
        ]
      }
    },
    {
      "id": "livestream-tricaster-ptz",
      "title": "Livestream-Setup: TriCaster + PTZ-Kameras",
      "category": "Technik-Setups",
      "difficulty": "mittel",
      "setupTimeMin": 240,
      "teamSize": "2-3",
      "tags": [
        "livestream",
        "tricaster",
        "ptz",
        "ndi",
        "regie"
      ],
      "relatedTools": [
        "jm-switcher",
        "jm-caption",
        "jm-titler",
        "jm-stage-display"
      ],
      "prerequisites": [
        "Strom 230 V / 10 A, einzeln abgesichert",
        "DSL-/Upload-Zugang vom Kunden",
        "Raumzugang am Aufbau- und am Showtag"
      ],
      "equipmentOwner": "jm",
      "crewRoles": [
        "Regie",
        "Media Operator Video (TriCaster)",
        "Media Operator Audio"
      ],
      "lastReviewed": "2026-06-24",
      "owner": "tech@jakobsmedien.com",
      "summary": "Kompaktes, mehrkamerataugliches Livestream-Setup mit TriCaster-Regie, PTZ-Kameras und DSGVO-konformem Stream — Basis für hybride Veranstaltungen.",
      "blocks": {
        "ingredients": [
          {
            "title": "Regie & Zuspielung",
            "items": [
              "NewTek TriCaster TC2 Elite (Broadcasting-System)",
              "2x Regie-Laptop (Programm-Feeds und Layouts)",
              "2-Wege-Intercom (z. B. GreenGo: Beltpacks, Antenne, Tischstation)"
            ]
          },
          {
            "title": "Kamera",
            "items": [
              "3x PTZ-Kamera (z. B. Panasonic AW-UE150) inkl. Stativ + 20 m Verkabelung",
              "PTZ-Bedienpanel (z. B. AW-RP150)",
              "FlexTally für Kamera-Tally",
              "Kamerapodest"
            ]
          },
          {
            "title": "Stream & Netzwerk",
            "items": [
              "DSGVO-Livestream (Server-Standort Deutschland)",
              "Livetranscoding (pro Stunde abgerechnet)",
              "Aufzeichnung → Video-on-Demand"
            ]
          },
          {
            "title": "Infrastruktur",
            "items": [
              "Regieverkleidung (Pipes & Drapes)",
              "Verkabelungspauschalen Video / Audio / Strom / Netzwerk",
              "Kabelkanäle (Defender)"
            ]
          }
        ],
        "steps": {
          "vor": [
            "Transport und Aufbau am Vortag",
            "PTZ-Positionen und Bildausschnitte einrichten",
            "TriCaster-Szenen/Layouts anlegen",
            "Intercom-Funkstrecken einmessen",
            "Stream-Endpunkt + Transcoding testen",
            "Abnahme und Probe mit Programm"
          ],
          "waehrend": [
            "Live-Regie steuert Szenen und Layouts",
            "Backstage-Kommunikation über 2-Wege-Intercom",
            "Recording für VOD mitlaufen lassen",
            "Stream-Gesundheit (Bitrate, Drops) überwachen"
          ],
          "nach": [
            "Aufzeichnung sichern",
            "VOD bereitstellen",
            "Abbau und Restabbau",
            "Material für Postproduktion übergeben"
          ]
        },
        "troubleshooting": [
          {
            "risk": "Kundeninternet instabil / ohne Haftung",
            "remedy": "Mobiler Backup-Uplink (Bonding/LTE), Stream-Bitrate konservativ wählen"
          },
          {
            "risk": "PTZ-Kamera reagiert nicht",
            "remedy": "Netzwerk/PoE prüfen, Ersatz-Patch, Kamera am Panel neu zuweisen"
          },
          {
            "risk": "Tally fehlt oder ist falsch",
            "remedy": "FlexTally-Zuordnung im TriCaster prüfen"
          },
          {
            "risk": "Intercom-Aussetzer",
            "remedy": "Antennenposition/Frequenz prüfen, Beltpack-Akkus tauschen"
          }
        ],
        "checklists": [
          {
            "title": "Aufbau",
            "items": [
              "Strom 230 V / 10 A abgesichert",
              "Netzwerk / Upload steht",
              "PTZ-Kameras zugewiesen und getallyt",
              "TriCaster-Layouts angelegt",
              "Intercom eingemessen"
            ]
          },
          {
            "title": "Vor Sendung",
            "items": [
              "Stream-Endpunkt live getestet",
              "Recording armiert",
              "Backup-Uplink bereit",
              "Probe mit Regie gelaufen"
            ]
          }
        ],
        "tips": [
          "Mehr Kamerabewegung und Inserts halten den Stream dynamisch — statische Totalen wirken schnell langweilig.",
          "Vorhandene Haustechnik (Licht, LED-Wand, Audiopult) vorab auf Verfügbarkeit und Funktion prüfen — nicht blind aufs Inventar verlassen."
        ]
      }
    },
    {
      "id": "ndi-workflow",
      "title": "NDI-Workflow im Studio-LAN",
      "category": "Technik-Setups",
      "difficulty": "mittel",
      "setupTimeMin": 60,
      "teamSize": "1",
      "tags": [
        "ndi",
        "netzwerk",
        "studio",
        "mdns",
        "bandbreite"
      ],
      "relatedTools": [
        "jm-ndi-screen-capture",
        "jm-switcher",
        "jm-titler",
        "jm-caption",
        "jm-studio-control"
      ],
      "prerequisites": [
        "Gigabit-LAN (möglichst dediziertes Produktions-Netz/VLAN)",
        "NDI-Runtime auf den beteiligten Rechnern",
        "Gleiche Subnetze für die Discovery"
      ],
      "equipmentOwner": "jm",
      "crewRoles": [
        "Media Operator / Netzwerk"
      ],
      "lastReviewed": "2026-06-24",
      "owner": "tech@jakobsmedien.com",
      "summary": "NDI-Quellen sauber im Studio-LAN bereitstellen und einbinden — Benennung, Bandbreite, Discovery und typische Fallstricke.",
      "blocks": {
        "ingredients": [
          {
            "title": "Netzwerk",
            "items": [
              "Gigabit-Switch, möglichst dediziertes NDI-/Produktions-VLAN",
              "Gleiche Subnetze für mDNS-Discovery"
            ]
          },
          {
            "title": "Quellen",
            "items": [
              "JM NDI Screen Capture (Bildschirm/Fenster)",
              "JM Titler (transparente Grafik), JM Caption (Untertitel)",
              "Kameras/Encoder mit NDI"
            ]
          },
          {
            "title": "Senken",
            "items": [
              "Bildmischer (TriCaster / vMix / OBS / JM Switcher)"
            ]
          }
        ],
        "steps": {
          "vor": [
            "Geräte ins gleiche Subnetz bringen, NDI-Runtime sicherstellen",
            "Quellen klar benennen (Gerät + Inhalt)",
            "Bandbreite grob kalkulieren (Full-NDI vs. NDI-HX)"
          ],
          "waehrend": [
            "Quellen im Mixer einbinden",
            "Auf Latenz und Framedrops achten",
            "Netzwerklast beobachten"
          ],
          "nach": [
            "Benennungs-/Portplan für die nächste Show dokumentieren"
          ]
        },
        "troubleshooting": [
          {
            "risk": "Quelle nicht sichtbar",
            "remedy": "Gleiches Subnetz/mDNS, Firewall, NDI-Runtime prüfen"
          },
          {
            "risk": "Ruckler / Drops",
            "remedy": "Bandbreite/Switch prüfen, NDI-HX erwägen"
          },
          {
            "risk": "Hohe Latenz",
            "remedy": "Netzlast und CPU der Quelle prüfen"
          }
        ],
        "checklists": [
          {
            "title": "Aufbau",
            "items": [
              "Gleiches Subnetz",
              "NDI-Runtime vorhanden",
              "Quellen sprechend benannt",
              "Bandbreite geprüft"
            ]
          },
          {
            "title": "Vor Live",
            "items": [
              "Alle Quellen im Mixer sichtbar",
              "Keine Drops/Latenzprobleme"
            ]
          }
        ],
        "tips": [
          "Eindeutige, sprechende NDI-Namen sparen im Live-Betrieb viel Zeit.",
          "Für viele Full-NDI-Streams das Netz dimensionieren oder gezielt NDI-HX nutzen."
        ]
      }
    },
    {
      "id": "bmukn-berlin",
      "title": "BMUKN Berlin — hybride Veranstaltung",
      "category": "Kunden-/Location-Setups",
      "difficulty": "anspruchsvoll",
      "setupTimeMin": 1440,
      "teamSize": "5",
      "tags": [
        "bmukn",
        "ministerium",
        "hybrid",
        "livestream",
        "location",
        "rahmenvertrag"
      ],
      "relatedTools": [
        "jm-switcher",
        "jm-caption",
        "jm-titler",
        "jm-qa",
        "jm-timer"
      ],
      "prerequisites": [
        "Strom 230 V / 10 A, einzeln abgesichert",
        "DSL-/Upload-Zugang vom Kunden (keine Haftung für Kundenleitung)",
        "Raumzugang am Aufbau- und am Produktionstag",
        "Crew-Anmeldung über Hausbetrieb (BMU/MKT-Rahmenvertrag)"
      ],
      "equipmentOwner": "gemischt",
      "crewRoles": [
        "Projektplanung",
        "Regie",
        "Media Operator Video (TriCaster) — via Hausbetrieb",
        "Media Operator Audio — via Hausbetrieb",
        "Media Operator Virtual — via Hausbetrieb"
      ],
      "lastReviewed": "2026-06-24",
      "owner": "tech@jakobsmedien.com",
      "summary": "Location-Profil für hybride Veranstaltungen im Bundesumweltministerium — vorhandene Haustechnik plus mitgebrachte JM-Regie/Kamera, abgeleitet aus der Preisverleihung Blauer Kompass.",
      "blocks": {
        "ingredients": [
          {
            "title": "Vorhandene Haustechnik (BMUKN-Eigentum)",
            "items": [
              "ARRI LED-Scheinwerfer für kameragerechte Ausleuchtung",
              "Optoma 130\" FHDQ LED-Wand inkl. Glasfaserverbindung und Verkabelung",
              "Yamaha QL1 Audiopult inkl. drahtloser Mikrofonierung, Monitoring für bis zu 8 Personen",
              "Bis 8 Funkmikrofone (Headset / Handheld)",
              "AnalogWay Pulse 2 Videoswitch inkl. Vorschaudisplays und Wandler",
              "MasterCue PPT-Klicker",
              "Verfahrbares Rednerpult inkl. 2x Schwanenhals-Mikrofon",
              "Bühnenvorschau 55\"",
              "Bühne 10 x 3 m"
            ]
          },
          {
            "title": "Mitgebrachte JM-Technik",
            "items": [
              "NewTek TriCaster TC2 Elite (Live-Regie, Recording)",
              "3x Panasonic AW-UE150 PTZ-Kamera inkl. Stativ + 20 m Verkabelung",
              "Panasonic AW-RP150 PTZ-Bedienpanel",
              "Cerevo FlexTally",
              "GreenGo-Intercom (Beltpacks, Antenne, Tischstation)",
              "2x Regie-Laptop"
            ]
          },
          {
            "title": "Stream & digitale Services",
            "items": [
              "DSGVO-Livestream (Server-Standort Deutschland)",
              "Livetranscoding (pro Stunde)",
              "Aufzeichnung → Video-on-Demand",
              "Publikums-Interaktion: Slido optional (oder JM Q&A als JM-eigene Alternative)"
            ]
          },
          {
            "title": "Infrastruktur",
            "items": [
              "Pipes & Drapes Regieverkleidung",
              "Verkabelungspauschalen Video / Audio / Strom / Netzwerk",
              "Defender-Kabelkanäle"
            ]
          }
        ],
        "steps": {
          "vor": [
            "In enger Abstimmung mit dem Veranstaltungsreferat des BMUKN planen",
            "Verfügbarkeit und Funktion der Haustechnik vorab bestätigen (nicht blind aufs Inventar verlassen)",
            "Crew über Hausbetrieb / MKT-Rahmenvertrag anmelden",
            "Transport (3,5 t) und Aufbau am Vortag",
            "PTZ-Positionen, TriCaster-Layouts, Intercom und Stream-Endpunkt einrichten",
            "Abnahme und ausführliche Probe am Vortag (ab ca. 15:00)"
          ],
          "waehrend": [
            "Live-Regie koordiniert Bühnenprogramm und Stream",
            "Standby und Betreuung im vereinbarten Zeitfenster",
            "Recording für das Highlight-Video mitlaufen lassen"
          ],
          "nach": [
            "Abbau (ab 17:30), Restabbau und Transport am Folgetag",
            "Postproduktion: 3-Min-Highlight-Film (Sichtung, Schnitt, Grafiken, Korrekturschleife, Color Grading, Rendering)",
            "Übergabe als Datei bzw. Embed-Code / iFrame"
          ]
        },
        "troubleshooting": [
          {
            "risk": "Kundeninternet ohne Haftung / instabil",
            "remedy": "Mobiler Backup-Uplink, Stream-Bitrate konservativ wählen"
          },
          {
            "risk": "Haustechnik nicht verfügbar oder defekt",
            "remedy": "Ersatz aus JM-Bestand einplanen, Funktion früh prüfen"
          },
          {
            "risk": "Raumzugang am Aufbautag fehlt",
            "remedy": "Zugang vorab mit dem Veranstaltungsreferat verbindlich klären"
          },
          {
            "risk": "Strom nicht separat abgesichert",
            "remedy": "Eigene Absicherung / Verteilung mitbringen"
          }
        ],
        "checklists": [
          {
            "title": "Vorbereitung",
            "items": [
              "Abstimmung mit Veranstaltungsreferat erfolgt",
              "Haustechnik-Verfügbarkeit bestätigt",
              "Crew via Hausbetrieb / MKT angemeldet",
              "Transport (3,5 t) gebucht"
            ]
          },
          {
            "title": "Showtag",
            "items": [
              "Probe am Vortag gelaufen",
              "Stream-Endpunkt live getestet",
              "Recording armiert (für Highlight-Film)",
              "Backup-Uplink bereit"
            ]
          }
        ],
        "tips": [
          "Als Rahmenvertragspartner darf JM die Haustechnik einrichten und nutzen — Verfügbarkeit und Funktion trotzdem immer früh prüfen.",
          "Preisverleihungen dynamischer gestalten: mehr Kamerabewegung, Inserts, Publikumsbeteiligung (Slido oder JM Q&A).",
          "Personal-Obergrenze von 10 h pro Person (inkl. Pausen und Reisezeiten) einplanen; Mehrkosten gesondert abrechnen."
        ]
      },
      "location": "BMUKN Berlin, Stresemannstr. 128-130"
    },
    {
      "id": "tool-jm-battle",
      "title": "JM Battle — BattleRap-Voting & Replay",
      "category": "Tool-Manuals",
      "difficulty": "mittel",
      "setupTimeMin": 25,
      "teamSize": "1-2",
      "tags": [
        "battle",
        "voting",
        "jury",
        "qr",
        "replay",
        "manual"
      ],
      "relatedTools": [
        "jm-battle",
        "jm-titler",
        "jm-recorder"
      ],
      "prerequisites": [
        "JM Battle installiert (über den Launcher)",
        "Netz/WLAN für das Publikums-Voting per QR-Code",
        "JM Titler im selben LAN (VS-Bauchbinde)",
        "Eine laufende Aufnahme als Quelle für den Instant-Replay"
      ],
      "equipmentOwner": "jm",
      "crewRoles": [
        "Battle-Operator"
      ],
      "lastReviewed": "2026-06-24",
      "owner": "tech@jakobsmedien.com",
      "summary": "BattleRap-Toolkit: zwei Kontrahenten, Runden mit Jury-Entscheid und Publikums-Voting per QR, VS-Bauchbinde via Titler, Instant-Replay aus der Aufnahme.",
      "blocks": {
        "ingredients": [
          {
            "title": "Voraussetzungen",
            "items": [
              "JM Battle (über den Launcher)",
              "Netz/WLAN für das QR-Voting der Gäste",
              "JM Titler im selben LAN (VS-Bauchbinde)",
              "Laufende Aufnahme (Quelle für den Instant-Replay)"
            ]
          }
        ],
        "steps": {
          "vor": [],
          "waehrend": [
            "Runde starten, VS-Bauchbinde einblenden",
            "Voting öffnen, dann schließen; Ergebnis anzeigen",
            "Bei Bedarf Instant-Replay (letzte Sekunden) erzeugen und abspielen"
          ],
          "nach": [
            "Ergebnisse sichern"
          ]
        },
        "troubleshooting": [
          {
            "risk": "QR-Voting kommt nicht an",
            "remedy": "Netz und Erreichbarkeit der Voting-Seite prüfen"
          },
          {
            "risk": "VS-Bauchbinde fehlt",
            "remedy": "JM Titler im selben LAN gestartet?"
          },
          {
            "risk": "Instant-Replay ist leer",
            "remedy": "Aufnahmequelle und Verbindung prüfen"
          }
        ],
        "checklists": [
          {
            "title": "Einrichtung",
            "items": [
              "Kontrahenten und Runden angelegt",
              "Titler verbunden (VS-Bauchbinde)",
              "Voting konfiguriert",
              "Aufnahme für Replay verbunden"
            ]
          },
          {
            "title": "Vor Live",
            "items": [
              "Test-Voting durchgeführt",
              "Test-Replay erzeugt"
            ]
          }
        ],
        "tips": [
          "Voting-Fenster bewusst kurz halten — das hält die Dramaturgie straff.",
          "Replay-Länge vorab testen, damit der Ausschnitt sitzt."
        ]
      }
    },
    {
      "id": "tool-jm-caption",
      "title": "JM Caption — Live-Untertitel (NDI) einrichten",
      "category": "Tool-Manuals",
      "difficulty": "mittel",
      "setupTimeMin": 20,
      "teamSize": "1",
      "tags": [
        "caption",
        "untertitel",
        "ndi",
        "whisper",
        "barrierefreiheit",
        "bitv",
        "manual"
      ],
      "relatedTools": [
        "jm-caption",
        "jm-switcher",
        "jm-studio-control"
      ],
      "prerequisites": [
        "Windows mit installierter NDI-Runtime",
        "JM Caption installiert (über den Launcher)",
        "Audioeingang (Mikrofon oder Saal-/Stream-Mix)",
        "Whisper-Modell (Basismodell mitgeliefert, größere nachladbar)"
      ],
      "equipmentOwner": "jm",
      "crewRoles": [
        "Media Operator (Untertitel)"
      ],
      "lastReviewed": "2026-06-24",
      "owner": "tech@jakobsmedien.com",
      "summary": "Live-Untertitel offline via whisper.cpp als transparente NDI-Quelle — für Politik-Streams, Pressekonferenzen und Barrierefreiheit (BITV).",
      "blocks": {
        "ingredients": [
          {
            "title": "Voraussetzungen",
            "items": [
              "Windows + NDI-Runtime",
              "JM Caption (über den Launcher)",
              "Audioeingang (Mikrofon oder besser ein sauberer Mix)",
              "Whisper-Modell (Basis mitgeliefert, größere für mehr Genauigkeit nachladbar)"
            ]
          }
        ],
        "steps": {
          "vor": [],
          "waehrend": [
            "Transkription starten",
            "Bei Fehlern „Hold\" zum Einfrieren und die letzte Zeile korrigieren",
            "Lesbarkeit und Timing im Blick behalten"
          ],
          "nach": [
            "Transkription stoppen"
          ]
        },
        "troubleshooting": [
          {
            "risk": "NDI-Quelle erscheint nicht im Mixer",
            "remedy": "NDI-Runtime und gleiches Subnetz prüfen"
          },
          {
            "risk": "Untertitel zu spät oder falsch",
            "remedy": "Modell/Sprache prüfen, Audioqualität verbessern"
          },
          {
            "risk": "Aussetzer / Ruckeln",
            "remedy": "CPU-Last beobachten, kleineres Modell wählen"
          }
        ],
        "checklists": [
          {
            "title": "Einrichtung",
            "items": [
              "Audioquelle gewählt",
              "Modell und Sprache gesetzt",
              "NDI-Quelle im Mixer sichtbar",
              "Companion (optional) verbunden"
            ]
          },
          {
            "title": "Vor Live",
            "items": [
              "Probesatz korrekt erkannt",
              "Hold getestet",
              "Lesbarkeit und Position ok"
            ]
          }
        ],
        "tips": [
          "Größeres Modell = bessere Genauigkeit, aber mehr CPU-Last — vorab unter Realbedingungen testen.",
          "Sauberer Ton (Pult-Mix statt Raummikro) verbessert die Erkennung deutlich."
        ]
      }
    },
    {
      "id": "tool-jm-qa",
      "title": "JM Q&A — Wortmeldungen & Saal-Fragen",
      "category": "Tool-Manuals",
      "difficulty": "mittel",
      "setupTimeMin": 20,
      "teamSize": "1-2",
      "tags": [
        "qa",
        "wortmeldung",
        "pressekonferenz",
        "townhall",
        "qr",
        "manual"
      ],
      "relatedTools": [
        "jm-qa",
        "jm-timer",
        "jm-titler"
      ],
      "prerequisites": [
        "JM Q&A installiert (über den Launcher)",
        "Netz/WLAN für die Saal-Einreichung per QR-Code",
        "JM Timer und JM Titler im selben LAN (für die Auto-Kopplung)"
      ],
      "equipmentOwner": "jm",
      "crewRoles": [
        "Moderations-Operator",
        "Moderation (Freigabe)"
      ],
      "lastReviewed": "2026-06-24",
      "owner": "tech@jakobsmedien.com",
      "summary": "Wortmeldungs- und Frage-Queue: der Saal reicht per QR vom Handy ein, per Klick kommt jemand ans Wort — steuert dabei Redezeit (Timer) und Bauchbinde (Titler) automatisch.",
      "blocks": {
        "ingredients": [
          {
            "title": "Voraussetzungen",
            "items": [
              "JM Q&A (über den Launcher)",
              "Netz/WLAN, über das die Gäste den QR-Code erreichen",
              "JM Timer und JM Titler im selben LAN"
            ]
          }
        ],
        "steps": {
          "vor": [],
          "waehrend": [
            "Eingehende Fragen moderieren und freigeben",
            "Per Klick jemanden ans Wort holen — Timer startet, Bauchbinde wird eingeblendet",
            "Queue abarbeiten"
          ],
          "nach": [
            "Queue/Statistik sichern (falls gewünscht)"
          ]
        },
        "troubleshooting": [
          {
            "risk": "QR-Einreichung kommt nicht an",
            "remedy": "Gleiches Netz und Erreichbarkeit der Einreich-Seite prüfen"
          },
          {
            "risk": "Timer/Titler reagieren nicht",
            "remedy": "Im selben LAN gestartet? mDNS/Firewall prüfen"
          }
        ],
        "checklists": [
          {
            "title": "Einrichtung",
            "items": [
              "QR-Einreichung aktiv",
              "Moderation/Freigabe gesetzt",
              "Timer und Titler gekoppelt"
            ]
          },
          {
            "title": "Vor Live",
            "items": [
              "Testfrage eingereicht und sichtbar",
              "Ans-Wort-holen getestet (Timer + Bauchbinde)"
            ]
          }
        ],
        "tips": [
          "Den Moderationsschritt aktiv nutzen, um Doppelungen und Unangemessenes zu filtern.",
          "Titler-Text ist vorwärtskompatibel (TITLER TEXT) — funktioniert auch mit älteren Titler-Ständen."
        ]
      }
    },
    {
      "id": "tool-jm-rundown",
      "title": "JM Rundown — Ablaufregie einrichten",
      "category": "Tool-Manuals",
      "difficulty": "mittel",
      "setupTimeMin": 30,
      "teamSize": "1",
      "tags": [
        "rundown",
        "ablauf",
        "regie",
        "companion",
        "mdns",
        "manual"
      ],
      "relatedTools": [
        "jm-rundown",
        "jm-timer",
        "jm-prompter",
        "jm-presenter",
        "jm-titler",
        "jm-switcher"
      ],
      "prerequisites": [
        "JM Rundown installiert (über den Launcher)",
        "Die anzusteuernden Tools im selben LAN (werden per mDNS gefunden)",
        "Bitfocus Companion für Fern-GO (optional)"
      ],
      "equipmentOwner": "jm",
      "crewRoles": [
        "Regie / Ablaufregie"
      ],
      "lastReviewed": "2026-06-24",
      "owner": "tech@jakobsmedien.com",
      "summary": "Zeilenbasierter Ablaufplan: ein GO startet pro Segment mehrere Tools gleichzeitig (Timer, Prompter, Presenter, Titler, Switcher).",
      "blocks": {
        "ingredients": [
          {
            "title": "Voraussetzungen",
            "items": [
              "JM Rundown installiert (über den Launcher)",
              "Ziel-Tools im selben LAN gestartet (Timer, Prompter, Presenter, Titler, Switcher)",
              "Optional: Bitfocus Companion für Fern-GO"
            ]
          },
          {
            "title": "Was pro Segment gesteuert wird",
            "items": [
              "Timer-Block (JM Timer)",
              "Prompter-Skript (JM Prompter)",
              "Presenter-Folie (JM Presenter)",
              "Titler-Bauchbinde (JM Titler)",
              "Switcher-Szene (JM Switcher)"
            ]
          }
        ],
        "steps": {
          "vor": [],
          "waehrend": [
            "Pro Segment GO drücken — feuert alle zugeordneten Aktionen gleichzeitig",
            "Live-Status / Tally im Blick behalten",
            "Bei Bedarf einzelne Aktionen per Override anpassen"
          ],
          "nach": [
            "`.jmrundown` sichern"
          ]
        },
        "troubleshooting": [
          {
            "risk": "Tool wird nicht gefunden",
            "remedy": "Gleiches Subnetz prüfen, Tool gestartet?, mDNS/Firewall"
          },
          {
            "risk": "GO feuert nicht alle Aktionen",
            "remedy": "Zuordnung je Zeile kontrollieren"
          },
          {
            "risk": "Companion-GO ohne Wirkung",
            "remedy": "Verbindung und gemeinsames LAN prüfen"
          }
        ],
        "checklists": [
          {
            "title": "Einrichtung",
            "items": [
              "Ziel-Tools laufen und sind gefunden",
              "Zeilen und Aktionen angelegt",
              "Live-Status grün",
              "Als .jmrundown gespeichert"
            ]
          },
          {
            "title": "Vor Live",
            "items": [
              "Probe-GO je Segment gelaufen",
              "Companion (optional) getestet"
            ]
          }
        ],
        "tips": [
          "Tools vor der Probe starten, damit sie im mDNS auftauchen und zuweisbar sind.",
          "Pro Zeile nur die wirklich nötigen Aktionen — das hält das GO vorhersehbar."
        ]
      }
    },
    {
      "id": "tool-jm-studio-control",
      "title": "JM Studio Control — Studio & TriCaster steuern",
      "category": "Tool-Manuals",
      "difficulty": "anspruchsvoll",
      "setupTimeMin": 45,
      "teamSize": "1",
      "tags": [
        "studio-control",
        "tricaster",
        "atem",
        "obs",
        "ptz",
        "companion",
        "gateway",
        "manual"
      ],
      "relatedTools": [
        "jm-studio-control",
        "jm-switcher",
        "jm-stage-display"
      ],
      "prerequisites": [
        "JM Studio Control installiert (über den Launcher)",
        "Studiogeräte im Netz erreichbar (TriCaster, ATEM, OBS, PTZ, Audio/Licht)",
        "Nutzer und Rollen festgelegt",
        "Bitfocus Companion (Gateway-Rolle „studio\", optional)"
      ],
      "equipmentOwner": "gemischt",
      "crewRoles": [
        "Studio-Operator / Technische Leitung"
      ],
      "lastReviewed": "2026-06-24",
      "owner": "tech@jakobsmedien.com",
      "summary": "Zentrale Studiosteuerung (TriCaster/ATEM/OBS/PTZ/Audio/Licht) mit Nutzerrollen, NDI-PGM-Vorschau und Companion-Gateway.",
      "blocks": {
        "ingredients": [
          {
            "title": "Voraussetzungen",
            "items": [
              "JM Studio Control (über den Launcher)",
              "Erreichbare Studiogeräte: Video-Mischer (TriCaster/ATEM/OBS), PTZ-Kameras, Audio, Licht",
              "Nutzer und Rollen",
              "Optional: Bitfocus Companion über die Gateway-Rolle „studio\""
            ]
          },
          {
            "title": "Gewerke",
            "items": [
              "Video-Mischer (TriCaster / ATEM / OBS)",
              "PTZ-Kameras",
              "Audio und Licht"
            ]
          }
        ],
        "steps": {
          "vor": [],
          "waehrend": [
            "Quellen und Szenen schalten, PTZ steuern, Audio/Licht bedienen",
            "PGM-Vorschau im Blick behalten",
            "Aktionen werden zentral protokolliert (auditiert)"
          ],
          "nach": [
            "Session/Logs sichern"
          ]
        },
        "troubleshooting": [
          {
            "risk": "Gerät nicht erreichbar",
            "remedy": "Netz/IP und Anmeldedaten prüfen"
          },
          {
            "risk": "Verb wirkt nicht",
            "remedy": "Richtige Primär-Instanz und Typ-Präfix prüfen"
          },
          {
            "risk": "Aktion verweigert",
            "remedy": "Nutzerrolle/Rechte kontrollieren"
          }
        ],
        "checklists": [
          {
            "title": "Einrichtung",
            "items": [
              "Geräte verbunden (Primär-Instanz je Typ)",
              "Rollen gesetzt",
              "PGM-Vorschau läuft",
              "Companion-Gateway (optional) aktiv"
            ]
          },
          {
            "title": "Vor Live",
            "items": [
              "Schalt-Test je Gewerk gelaufen",
              "Rechte/Rollen geprüft"
            ]
          }
        ],
        "tips": [
          "Pro Gerätetyp genau eine Primär-Instanz festlegen — das vermeidet Mehrdeutigkeit beim Schalten.",
          "Das Companion-Gateway bündelt alle Gewerke auf einer Rolle, statt jedes Gerät einzeln anzubinden."
        ]
      }
    },
    {
      "id": "tool-jm-switcher",
      "title": "JM Switcher — Video-Mischer einrichten",
      "category": "Tool-Manuals",
      "difficulty": "mittel",
      "setupTimeMin": 30,
      "teamSize": "1",
      "tags": [
        "switcher",
        "ndi",
        "streaming",
        "rtmp",
        "companion",
        "manual"
      ],
      "relatedTools": [
        "jm-switcher",
        "jm-ndi-screen-capture",
        "jm-titler",
        "jm-stage-display"
      ],
      "prerequisites": [
        "JM Switcher installiert (über den Launcher)",
        "NDI-Runtime, falls NDI-Quellen genutzt werden",
        "Capture-Karte inkl. Treiber, falls SDI/HDMI-Quellen",
        "RTMP-Ziel (Stream-Key) + stabile Upload-Leitung (nur fürs Streaming)",
        "Bitfocus Companion für die Fernsteuerung (optional)"
      ],
      "equipmentOwner": "jm",
      "crewRoles": [
        "Media Operator (Bildregie)"
      ],
      "lastReviewed": "2026-06-24",
      "owner": "tech@jakobsmedien.com",
      "summary": "Softwarebasierter Video-Mischer mit Program/Preview, NDI-/Capture-/Bildschirm-Quellen, Aufnahme und RTMP-Ausgang — Einrichtung und Live-Bedienung.",
      "blocks": {
        "ingredients": [
          {
            "title": "Voraussetzungen",
            "items": [
              "JM Switcher installiert (über den Launcher)",
              "NDI-Runtime (für NDI-Quellen) bzw. Capture-Karten-Treiber (für SDI/HDMI)",
              "RTMP-Ziel + Upload-Leitung (nur fürs Streaming)"
            ]
          },
          {
            "title": "Quellen",
            "items": [
              "Bildschirm oder einzelnes Fenster",
              "NDI-Quellen aus dem LAN (z. B. JM NDI Screen Capture, JM Titler)",
              "Capture-Karte (SDI/HDMI)"
            ]
          }
        ],
        "steps": {
          "vor": [],
          "waehrend": [
            "Quelle in Preview wählen",
            "Mit Cut hart oder mit Auto-Dissolve weich auf Program schalten",
            "Aufnahme und/oder Stream starten",
            "Stream-Status (Bitrate, Drops) und Audiopegel beobachten"
          ],
          "nach": [
            "Stream beenden, Aufnahme stoppen",
            "Aufnahme sichern und übergeben"
          ]
        },
        "troubleshooting": [
          {
            "risk": "NDI-Quelle erscheint nicht",
            "remedy": "Gleiches Subnetz prüfen, Firewall/mDNS freigeben"
          },
          {
            "risk": "Kein Bild von der Capture-Karte",
            "remedy": "Treiber prüfen, Gerät nicht von anderem Programm belegt"
          },
          {
            "risk": "Stream bricht ab",
            "remedy": "Bitrate senken, Upload prüfen, Backup-Uplink bereithalten"
          },
          {
            "risk": "Kein Ton im Stream",
            "remedy": "Audioquelle zugeordnet? Pegel/Mute prüfen"
          }
        ],
        "checklists": [
          {
            "title": "Einrichtung",
            "items": [
              "Quellen hinzugefügt",
              "Audio zugeordnet und gepegelt",
              "Aufnahme-Zielordner gesetzt",
              "RTMP-Verbindung getestet",
              "Companion (optional) verbunden"
            ]
          },
          {
            "title": "Vor Live",
            "items": [
              "Program/Preview korrekt",
              "Cut und Dissolve getestet",
              "Aufnahme armiert",
              "Pegel ok"
            ]
          }
        ],
        "tips": [
          "NDI-Quellen tauchen automatisch im LAN auf (mDNS) — alle Geräte ins gleiche Subnetz.",
          "JM Titler als eigene, transparente NDI-Quelle über das Programmbild legen.",
          "Vor Live einmal Cut und Auto-Dissolve durchspielen."
        ]
      }
    },
    {
      "id": "tool-jm-timer",
      "title": "JM Timer — Countdown & Sprecher-Timer",
      "category": "Tool-Manuals",
      "difficulty": "einfach",
      "setupTimeMin": 10,
      "teamSize": "1",
      "tags": [
        "timer",
        "countdown",
        "sprecher",
        "companion",
        "manual"
      ],
      "relatedTools": [
        "jm-timer",
        "jm-stage-display",
        "jm-rundown"
      ],
      "prerequisites": [
        "JM Timer installiert (über den Launcher)",
        "Zweiter Bildschirm / Sprecher-Monitor (optional)",
        "Netzwerk / Bitfocus Companion für die Fernsteuerung (optional)"
      ],
      "equipmentOwner": "jm",
      "crewRoles": [
        "Regie / Media Operator"
      ],
      "lastReviewed": "2026-06-24",
      "owner": "tech@jakobsmedien.com",
      "summary": "Countdown- und Produktions-Timer mit Sprecherfenster und Fernsteuerung — Einrichtung und Bedienung im Live-Betrieb.",
      "blocks": {
        "ingredients": [
          {
            "title": "Voraussetzungen",
            "items": [
              "JM Timer installiert (über den Launcher)",
              "Optional: zweiter Monitor für das Sprecherfenster",
              "Optional: Netzwerk / Bitfocus Companion für die Fernsteuerung"
            ]
          }
        ],
        "steps": {
          "vor": [],
          "waehrend": [
            "Timer starten / stoppen / zurücksetzen",
            "Bei Bedarf eine Kurznachricht für die Bühne einblenden",
            "Over-Time (Rotphase) im Blick behalten"
          ],
          "nach": [
            "Timer für das nächste Segment zurücksetzen"
          ]
        },
        "troubleshooting": [
          {
            "risk": "Sprecherfenster auf falschem Monitor",
            "remedy": "Fenster auf den Talent-Monitor ziehen, Vollbild setzen"
          },
          {
            "risk": "Fernsteuerung reagiert nicht",
            "remedy": "Gleiches LAN prüfen, Companion-Verbindung kontrollieren"
          }
        ],
        "checklists": [
          {
            "title": "Einrichtung",
            "items": [
              "Presets je Segment angelegt",
              "Sprecherfenster auf Talent-Monitor",
              "Fernsteuerung (optional) verbunden"
            ]
          },
          {
            "title": "Vor Live",
            "items": [
              "Test-Start gelaufen",
              "Auf Stage Display sichtbar"
            ]
          }
        ],
        "tips": [
          "Mit JM Rundown koppeln: pro Segment startet der Timer automatisch.",
          "Den Countdown zusätzlich auf JM Stage Display für die Crew anzeigen."
        ]
      }
    }
  ]
}
